tinympc/interface.py
tinympc/ext_tinympc.pypy310-pp73-x86_64-linux-gnu.so
tinympc/__init__.py
tinympc/codegen/__init__.py
tinympc/codegen/pywrapper/CMakeLists.txt
tinympc/codegen/pywrapper/setup.py
tinympc/codegen/pywrapper/bindings.cpp
tinympc/codegen/pywrapper/__init__.py
tinympc/codegen/codegen_src/include/Eigen.h
tinympc/codegen/codegen_src/include/Eigen/SVD
tinympc/codegen/codegen_src/include/Eigen/KLUSupport
tinympc/codegen/codegen_src/include/Eigen/Jacobi
tinympc/codegen/codegen_src/include/Eigen/Geometry
tinympc/codegen/codegen_src/include/Eigen/Sparse
tinympc/codegen/codegen_src/include/Eigen/MetisSupport
tinympc/codegen/codegen_src/include/Eigen/QR
tinympc/codegen/codegen_src/include/Eigen/QtAlignedMalloc
tinympc/codegen/codegen_src/include/Eigen/StdVector
tinympc/codegen/codegen_src/include/Eigen/PaStiXSupport
tinympc/codegen/codegen_src/include/Eigen/Householder
tinympc/codegen/codegen_src/include/Eigen/ThreadPool
tinympc/codegen/codegen_src/include/Eigen/SparseCholesky
tinympc/codegen/codegen_src/include/Eigen/SuperLUSupport
tinympc/codegen/codegen_src/include/Eigen/OrderingMethods
tinympc/codegen/codegen_src/include/Eigen/IterativeLinearSolvers
tinympc/codegen/codegen_src/include/Eigen/UmfPackSupport
tinympc/codegen/codegen_src/include/Eigen/SPQRSupport
tinympc/codegen/codegen_src/include/Eigen/SparseCore
tinympc/codegen/codegen_src/include/Eigen/Eigenvalues
tinympc/codegen/codegen_src/include/Eigen/PardisoSupport
tinympc/codegen/codegen_src/include/Eigen/SparseLU
tinympc/codegen/codegen_src/include/Eigen/Dense
tinympc/codegen/codegen_src/include/Eigen/Eigen
tinympc/codegen/codegen_src/include/Eigen/StdList
tinympc/codegen/codegen_src/include/Eigen/SparseQR
tinympc/codegen/codegen_src/include/Eigen/LU
tinympc/codegen/codegen_src/include/Eigen/AccelerateSupport
tinympc/codegen/codegen_src/include/Eigen/StdDeque
tinympc/codegen/codegen_src/include/Eigen/Cholesky
tinympc/codegen/codegen_src/include/Eigen/Core
tinympc-0.0.2.dist-info/METADATA
tinympc-0.0.2.dist-info/WHEEL
tinympc-0.0.2.dist-info/RECORD
tinympc-0.0.2.dist-info/licenses/LICENSE
