Metadata-Version: 2.1
Name: tinympc
Version: 0.0.2
Summary: Python wrapper for TinyMPC
Author-Email: Sam Schoedel <seschoedel@gmail.com>, Khai Nguyen <khai.nx1201@gmail.com>
License: MIT License
Classifier: Programming Language :: Python :: 3
Classifier: License :: OSI Approved :: MIT License
Classifier: Operating System :: OS Independent
Project-URL: Homepage, https://tinympc.org
Requires-Python: >=3.7
Requires-Dist: numpy>=1.7
Requires-Dist: scipy<1.12.0,>=0.13.2
Requires-Dist: setuptools
